strong_image_creation/__init__.py
strong_image_creation/strong_image_creation.py
strong_image_creation-0.9.1.dist-info/METADATA
strong_image_creation-0.9.1.dist-info/WHEEL
strong_image_creation-0.9.1.dist-info/entry_points.txt
strong_image_creation-0.9.1.dist-info/top_level.txt
strong_image_creation-0.9.1.dist-info/RECORD
